jkq/qfr/__init__.py
jkq/qfr/pyqfr.cpython-310-darwin.so
jkq.qfr-1.7.3.dist-info/LICENSE.md
jkq.qfr-1.7.3.dist-info/METADATA
jkq.qfr-1.7.3.dist-info/WHEEL
jkq.qfr-1.7.3.dist-info/top_level.txt
jkq.qfr-1.7.3.dist-info/RECORD
