Metadata-Version: 2.1
Name: jkq.qfr
Version: 1.7.3
Summary: QFR - A JKQ tool for Quantum Functionality Representation
Home-page: https://iic.jku.at/eda/research/quantum_dd
Author: Lukas Burgholzer
Author-email: lukas.burgholzer@jku.at
License: MIT
Project-URL: Source, https://github.com/iic-jku/qfr/
Project-URL: Tracker, https://github.com/iic-jku/qfr/issues
Project-URL: Research, https://iic.jku.at/eda/research/quantum_dd
Keywords: jkq quantum decision_diagrams
Platform: UNKNOWN
Classifier: Development Status :: 5 - Production/Stable
Classifier: Programming Language :: Python :: 3
Classifier: Programming Language :: C++
Classifier: License :: OSI Approved :: MIT License
Classifier: Operating System :: Microsoft :: Windows
Classifier: Operating System :: MacOS
Classifier: Operating System :: POSIX :: Linux
Classifier: Intended Audience :: Science/Research
Classifier: Natural Language :: English
Classifier: Topic :: Scientific/Engineering :: Electronic Design Automation (EDA)
License-File: LICENSE.md
